github_to_sqlite/__init__.py
github_to_sqlite/cli.py
github_to_sqlite/utils.py
github_to_sqlite-2.9.dist-info/LICENSE
github_to_sqlite-2.9.dist-info/METADATA
github_to_sqlite-2.9.dist-info/WHEEL
github_to_sqlite-2.9.dist-info/entry_points.txt
github_to_sqlite-2.9.dist-info/top_level.txt
github_to_sqlite-2.9.dist-info/RECORD
