Metadata-Version: 2.1
Name: github-to-sqlite
Version: 2.9
Summary: Save data from GitHub to a SQLite database
Home-page: https://github.com/dogsheep/github-to-sqlite
Author: Simon Willison
License: Apache License, Version 2.0
License-File: LICENSE
Requires-Dist: sqlite-utils >=2.7.2
Requires-Dist: requests
Requires-Dist: PyYAML
Provides-Extra: test
Requires-Dist: pytest ; extra == 'test'
Requires-Dist: requests-mock ; extra == 'test'
Requires-Dist: bs4 ; extra == 'test'
